MANIFEST.in
README.rst
setup.py
willie.py
/tmp/tmpoF0cLh/willie
sopel/__init__.py
test/test_db.py
test/test_trigger.py
willie/__init__.py
willie/bot.py
willie/coretasks.py
willie/db.py
willie/formatting.py
willie/irc.py
willie/logger.py
willie/module.py
willie/test_tools.py
willie/trigger.py
willie/web.py
willie.egg-info/PKG-INFO
willie.egg-info/SOURCES.txt
willie.egg-info/dependency_links.txt
willie.egg-info/requires.txt
willie.egg-info/top_level.txt
willie/config/__init__.py
willie/config/core_section.py
willie/config/types.py
willie/modules/__init__.py
willie/modules/admin.py
willie/modules/adminchannel.py
willie/modules/announce.py
willie/modules/bugzilla.py
willie/modules/calc.py
willie/modules/chanlogs.py
willie/modules/clock.py
willie/modules/countdown.py
willie/modules/currency.py
willie/modules/dice.py
willie/modules/etymology.py
willie/modules/find.py
willie/modules/find_updates.py
willie/modules/github.py
willie/modules/help.py
willie/modules/ip.py
willie/modules/ipython.py
willie/modules/isup.py
willie/modules/lmgtfy.py
willie/modules/meetbot.py
willie/modules/movie.py
willie/modules/ping.py
willie/modules/radio.py
willie/modules/rand.py
willie/modules/reddit.py
willie/modules/reload.py
willie/modules/remind.py
willie/modules/rss.py
willie/modules/safety.py
willie/modules/search.py
willie/modules/seen.py
willie/modules/spellcheck.py
willie/modules/tell.py
willie/modules/tld.py
willie/modules/translate.py
willie/modules/unicode_info.py
willie/modules/units.py
willie/modules/uptime.py
willie/modules/url.py
willie/modules/version.py
willie/modules/weather.py
willie/modules/wikipedia.py
willie/modules/wiktionary.py
willie/modules/xkcd.py
willie/tools/__init__.py
willie/tools/calculation.py
willie/tools/jobs.py
willie/tools/time.py