Metadata-Version: 1.1
Name: willie
Version: 5.5.1
Summary: Simple and extendible IRC bot
Home-page: http://willie.dftba.net/
Author: Edward Powell
Author-email: powell.518@gmail.com
License: Eiffel Forum License, version 2
Platform: L
Platform: i
Platform: n
Platform: u
Platform: x
Platform:  
Platform: x
Platform: 8
Platform: 6
Platform: ,
Platform:  
Platform: x
Platform: 8
Platform: 6
Platform: -
Platform: 6
Platform: 4
Requires: feedparser
Requires: pytz
Requires: lxml
Requires: praw
Requires: pyenchant
Requires: pygeoip
Requires: backports.ssl_match_hostname
